molgenis/eucan_connect/__init__.py
molgenis/eucan_connect/data_assembler.py
molgenis/eucan_connect/errors.py
molgenis/eucan_connect/eucan.py
molgenis/eucan_connect/eucan_client.py
molgenis/eucan_connect/importer.py
molgenis/eucan_connect/model.py
molgenis/eucan_connect/printer.py
molgenis/eucan_connect/source_collector.py
molgenis/eucan_connect/table_info.py
molgenis/eucan_connect/transformer.py
molgenis/eucan_connect/utils.py
molgenis/eucan_connect/validator.py
molgenis/eucan_connect/birthcohorts/__init__.py
molgenis/eucan_connect/birthcohorts/birthcohorts_assembler.py
molgenis/eucan_connect/birthcohorts/birthcohorts_transformer.py
molgenis/eucan_connect/datacatalogue/__init__.py
molgenis/eucan_connect/datacatalogue/datacatalogue_assembler.py
molgenis/eucan_connect/datacatalogue/datacatalogue_transformer.py
molgenis/eucan_connect/mica/__init__.py
molgenis/eucan_connect/mica/mica_assembler.py
molgenis/eucan_connect/mica/mica_transformer.py
molgenis_py_eucan_connect-1.0.0.dist-info/LICENSE.txt
molgenis_py_eucan_connect-1.0.0.dist-info/METADATA
molgenis_py_eucan_connect-1.0.0.dist-info/WHEEL
molgenis_py_eucan_connect-1.0.0.dist-info/top_level.txt
molgenis_py_eucan_connect-1.0.0.dist-info/RECORD
