Metadata-Version: 2.1
Name: molgenis-py-eucan-connect
Version: 1.0.0
Summary: MOLGENIS Python tooling for the EUCAN-Connect Catalogue
Home-page: https://github.com/molgenis/molgenis-py-eucan-connect
Author: Dieuwke Roelofs-Prins
Author-email: d.t.roelofs-prins@umcg.nl
License: LGPL-3.0-only
Project-URL: Source, https://github.com/molgenis/molgenis-py-eucan-connect
Platform: any
Classifier: License :: OSI Approved :: GNU Lesser General Public License v3 (LGPLv3)
Classifier: Programming Language :: Python
Classifier: Programming Language :: Python :: 3 :: Only
Classifier: Programming Language :: Python :: 3.10
Requires-Python: >=3.10
License-File: LICENSE.txt
Requires-Dist: molgenis-py-client
Requires-Dist: pandas
Requires-Dist: requests
Requires-Dist: unidecode
Provides-Extra: testing
Requires-Dist: setuptools ; extra == 'testing'
Requires-Dist: pytest ; extra == 'testing'
Requires-Dist: pytest-cov ; extra == 'testing'
